{
  "content": [
    {
      "id": "10aea5e",
      "elType": "container",
      "settings": {
        "content_width": "full",
        "flex_direction": "column",
        "flex_gap": {
          "unit": "px",
          "size": 16,
          "column": "16",
          "row": "16",
          "isLinked": true
        },
        "padding": {
          "unit": "px",
          "top": "40",
          "right": "20",
          "bottom": "8",
          "left": "20",
          "isLinked": false
        }
      },
      "elements": [
        {
          "id": "5a5f219",
          "elType": "widget",
          "widgetType": "heading",
          "settings": {
            "title": "Patient information",
            "header_size": "h1",
            "align": "left"
          },
          "elements": []
        }
      ]
    },
    {
      "id": "7095a0f",
      "elType": "container",
      "settings": {
        "content_width": "full",
        "flex_direction": "column",
        "flex_gap": {
          "unit": "px",
          "size": 16,
          "column": "16",
          "row": "16",
          "isLinked": true
        },
        "padding": {
          "unit": "px",
          "top": "24",
          "right": "20",
          "bottom": "24",
          "left": "20",
          "isLinked": false
        }
      },
      "elements": [
        {
          "id": "1bc502a",
          "elType": "widget",
          "widgetType": "shortcode",
          "settings": {
            "shortcode": "[coleebri_catalogue widget=\"patient-info\" branding=\"none\" height=\"920\"]"
          },
          "elements": []
        }
      ]
    }
  ],
  "page_settings": {
    "hide_title": "yes"
  },
  "version": "0.4",
  "title": "Patient information",
  "type": "page"
}